COPYING
MANIFEST.in
README.txt
libldap.py
setup.cfg
setup.py
C/LDAPControls.c
C/LDAPControls.h
C/LDAPModObject.c
C/LDAPModObject.h
C/LDAPObject.c
C/LDAPObject.h
C/LDAPSchema.c
C/LDAPSchema.h
C/libldap.c
C/libldap.h
py3_libldap.egg-info/PKG-INFO
py3_libldap.egg-info/SOURCES.txt
py3_libldap.egg-info/dependency_links.txt
py3_libldap.egg-info/top_level.txt