Metadata-Version: 1.1
Name: py3-libldap
Version: 1.1
Summary: OpenLDAP library wrapper
Home-page: https://github.com/ylgg/libldap
Author: Yves Legrandgerard
Author-email: ylg@pps.univ-paris-diderot.fr
License: DWTFYWT
Download-URL: https://github.com/ylgg/libldap/archive/1.0.tar.gz
Platform: Linux
Platform: FreeBSD
